qssimport/__init__.py
qssimport/stylesheet.py
qssimport/version.py
qssimport-1.0.2.dist-info/METADATA
qssimport-1.0.2.dist-info/WHEEL
qssimport-1.0.2.dist-info/top_level.txt
qssimport-1.0.2.dist-info/RECORD
