Metadata-Version: 2.1
Name: qssimport
Version: 1.0.2
Summary: Merge qss files by using @import
Home-page: https://github.com/c385/qssimport
Author: Chris Souza
Author-email: chris.souza3425@gmail.com
License: MIT
Platform: UNKNOWN
Classifier: Intended Audience :: End Users/Desktop
Classifier: Programming Language :: Python :: 3.6
Classifier: Programming Language :: Python :: 3.7
Classifier: Programming Language :: Python :: 3 :: Only
Requires-Python: >=3.4
